nwpeval/__init__.py
nwpeval/nwpeval.py
nwpeval/utils.py
nwpeval/metrics/__init__.py
nwpeval/metrics/_base.py
nwpeval/metrics/acc.py
nwpeval/metrics/aev.py
nwpeval/metrics/ass.py
nwpeval/metrics/ba.py
nwpeval/metrics/bhattacharyya.py
nwpeval/metrics/bss.py
nwpeval/metrics/chernoff.py
nwpeval/metrics/chisquare.py
nwpeval/metrics/cosine_similarity.py
nwpeval/metrics/csi.py
nwpeval/metrics/eds.py
nwpeval/metrics/ets.py
nwpeval/metrics/evs.py
nwpeval/metrics/f1.py
nwpeval/metrics/far.py
nwpeval/metrics/fb.py
nwpeval/metrics/fss.py
nwpeval/metrics/fv.py
nwpeval/metrics/gain.py
nwpeval/metrics/geometric_mean.py
nwpeval/metrics/gmb.py
nwpeval/metrics/gss.py
nwpeval/metrics/harmonic_mean.py
nwpeval/metrics/hellinger.py
nwpeval/metrics/hkd.py
nwpeval/metrics/hss.py
nwpeval/metrics/intersection.py
nwpeval/metrics/iqr.py
nwpeval/metrics/jaccard.py
nwpeval/metrics/jsdiv.py
nwpeval/metrics/lehmer_mean.py
nwpeval/metrics/lift.py
nwpeval/metrics/lmbe.py
nwpeval/metrics/mad.py
nwpeval/metrics/mae.py
nwpeval/metrics/mape.py
nwpeval/metrics/mbd.py
nwpeval/metrics/mcc.py
nwpeval/metrics/mkldiv.py
nwpeval/metrics/nae.py
nwpeval/metrics/nmse.py
nwpeval/metrics/npv.py
nwpeval/metrics/nrmse.py
nwpeval/metrics/orss.py
nwpeval/metrics/pcc.py
nwpeval/metrics/pod.py
nwpeval/metrics/pss.py
nwpeval/metrics/qss.py
nwpeval/metrics/r2.py
nwpeval/metrics/renyi.py
nwpeval/metrics/rmb.py
nwpeval/metrics/rmse.py
nwpeval/metrics/rpss.py
nwpeval/metrics/rss.py
nwpeval/metrics/sbs.py
nwpeval/metrics/sdr.py
nwpeval/metrics/sedi.py
nwpeval/metrics/seds.py
nwpeval/metrics/smse.py
nwpeval/metrics/tsallis.py
nwpeval/metrics/tse.py
nwpeval/metrics/tv.py
nwpeval/metrics/vif.py
nwpeval/metrics/wasserstein.py
nwpeval/metrics/wmae.py
nwpeval-1.6.0.dist-info/licenses/LICENSE
nwpeval-1.6.0.dist-info/METADATA
nwpeval-1.6.0.dist-info/WHEEL
nwpeval-1.6.0.dist-info/top_level.txt
nwpeval-1.6.0.dist-info/RECORD
