Metadata-Version: 2.4
Name: nwpeval
Version: 1.6.0
Summary: A package for computing metrics for NWP model evaluation
Author: Debasish Mahapatra
Author-email: debasish.atmos@gmail.com | debasish.mahapatra@ugent.be
Classifier: Development Status :: 4 - Beta
Classifier: Intended Audience :: Science/Research
Classifier: License :: OSI Approved :: MIT License
Classifier: Programming Language :: Python :: 3
Classifier: Programming Language :: Python :: 3.6
Classifier: Programming Language :: Python :: 3.7
Classifier: Programming Language :: Python :: 3.8
Classifier: Programming Language :: Python :: 3.9
Classifier: Operating System :: OS Independent
License-File: LICENSE
Requires-Dist: numpy>=1.20.0
Requires-Dist: pygrib>=2.1.0
Requires-Dist: xarray>=0.18.0
Requires-Dist: scipy>=1.6.0
Requires-Dist: pandas>=1.2.0
Requires-Dist: matplotlib>=3.3.0
Dynamic: author
Dynamic: author-email
Dynamic: classifier
Dynamic: description
Dynamic: description-content-type
Dynamic: license-file
Dynamic: requires-dist
Dynamic: summary
